pycmsgen.cp37-win_amd64.pyd
pycmsgen-6.1.1.dist-info/AUTHORS
pycmsgen-6.1.1.dist-info/LICENSE.txt
pycmsgen-6.1.1.dist-info/METADATA
pycmsgen-6.1.1.dist-info/WHEEL
pycmsgen-6.1.1.dist-info/top_level.txt
pycmsgen-6.1.1.dist-info/RECORD
