Metadata-Version: 2.1
Name: pycmsgen
Version: 6.1.1
Summary: Bindings to CMSGen, uniform-like sampler
Home-page: https://github.com/meelgroup/cmsgen
Author-email: Mate Soos <soos.mate@gmail.com>
Maintainer-email: Mate Soos <soos.mate@gmail.com>
License: CryptoMiniSat Copyright (c) Mate Soos 2009-2018
Keywords: sat,sampling
Classifier: Development Status :: 4 - Beta
Classifier: Intended Audience :: Developers
Classifier: Operating System :: OS Independent
Classifier: Programming Language :: C++
Classifier: Programming Language :: Python :: 3
Classifier: Programming Language :: Python :: 3.5
Classifier: License :: OSI Approved :: MIT License
Classifier: Topic :: Utilities
Requires-Python: >=3.5
License-File: LICENSE.txt
License-File: AUTHORS
